kpops/api/__init__.py
kpops/api/logs.py
kpops/api/options.py
kpops/cli/__init__.py
kpops/cli/main.py
kpops/cli/utils.py
kpops/component_handlers/__init__.py
kpops/component_handlers/helm_wrapper/__init__.py
kpops/component_handlers/helm_wrapper/dry_run_handler.py
kpops/component_handlers/helm_wrapper/exception.py
kpops/component_handlers/helm_wrapper/helm.py
kpops/component_handlers/helm_wrapper/helm_diff.py
kpops/component_handlers/helm_wrapper/model.py
kpops/component_handlers/helm_wrapper/utils.py
kpops/component_handlers/kafka_connect/__init__.py
kpops/component_handlers/kafka_connect/connect_wrapper.py
kpops/component_handlers/kafka_connect/exception.py
kpops/component_handlers/kafka_connect/kafka_connect_handler.py
kpops/component_handlers/kafka_connect/model.py
kpops/component_handlers/kafka_connect/timeout.py
kpops/component_handlers/kubernetes/__init__.py
kpops/component_handlers/kubernetes/pvc_handler.py
kpops/component_handlers/kubernetes/utils.py
kpops/component_handlers/schema_handler/__init__.py
kpops/component_handlers/schema_handler/schema_handler.py
kpops/component_handlers/schema_handler/schema_provider.py
kpops/component_handlers/topic/__init__.py
kpops/component_handlers/topic/exception.py
kpops/component_handlers/topic/handler.py
kpops/component_handlers/topic/model.py
kpops/component_handlers/topic/proxy_wrapper.py
kpops/component_handlers/topic/utils.py
kpops/component_handlers/utils/__init__.py
kpops/component_handlers/utils/exception.py
kpops/components/base_components/__init__.py
kpops/components/base_components/base_defaults_component.py
kpops/components/base_components/cleaner.py
kpops/components/base_components/helm_app.py
kpops/components/base_components/kafka_app.py
kpops/components/base_components/kafka_connector.py
kpops/components/base_components/kubernetes_app.py
kpops/components/base_components/pipeline_component.py
kpops/components/base_components/models/__init__.py
kpops/components/base_components/models/from_section.py
kpops-10.7.0.dist-info/METADATA
kpops-10.7.0.dist-info/WHEEL
kpops-10.7.0.dist-info/entry_points.txt
kpops-10.7.0.dist-info/licenses/LICENSE
kpops-10.7.0.dist-info/RECORD
