Metadata-Version: 2.4
Name: kpops
Version: 10.7.0
Summary: KPOps is a tool to deploy Kafka pipelines to Kubernetes
Author-email: bakdata <opensource@bakdata.com>
License-File: LICENSE
Keywords: kafka,kubernetes,pipelines,stream-processing
Classifier: Environment :: Console
Classifier: Intended Audience :: Developers
Classifier: License :: OSI Approved :: MIT License
Classifier: Operating System :: OS Independent
Classifier: Topic :: Software Development
Classifier: Topic :: Software Development :: Libraries
Classifier: Topic :: Software Development :: Libraries :: Python Modules
Classifier: Typing :: Typed
Requires-Python: >=3.11
Requires-Dist: anyio>=4.3.0
Requires-Dist: cachetools>=5.2.0
Requires-Dist: croniter>=3.0.3
Requires-Dist: dictdiffer>=0.9.0
Requires-Dist: httpx>=0.24.1
Requires-Dist: lightkube>=0.15.3
Requires-Dist: networkx>=3.1
Requires-Dist: pydantic-settings>=2.0.3
Requires-Dist: pydantic>=2.10.6
Requires-Dist: pyhumps>=3.7.3
Requires-Dist: python-schema-registry-client>=2.4.1
Requires-Dist: pyyaml>=6.0
Requires-Dist: rich>=12.4.4
Requires-Dist: typer>=0.12.5
